zipkin/__init__.py
zipkin/api.py
zipkin/binding/__init__.py
zipkin/binding/celery/__init__.py
zipkin/binding/celery/events.py
zipkin/binding/celery/impl.py
zipkin/binding/django/__init__.py
zipkin/binding/django/apps.py
zipkin/binding/django/middleware.py
zipkin/binding/flask/__init__.py
zipkin/binding/flask/events.py
zipkin/binding/flask/impl.py
zipkin/binding/psycopg2/__init__.py
zipkin/binding/psycopg2/tracer.py
zipkin/binding/pyramid/__init__.py
zipkin/binding/pyramid/config.py
zipkin/binding/pyramid/pyramidhook.py
zipkin/binding/requests/__init__.py
zipkin/binding/requests/events.py
zipkin/binding/requests/impl.py
zipkin/binding/sqlalchemy/__init__.py
zipkin/binding/sqlalchemy/events.py
zipkin/binding/sqlalchemy/impl.py
zipkin/binding/xmlrpclib/__init__.py
zipkin/binding/xmlrpclib/events.py
zipkin/binding/xmlrpclib/impl.py
zipkin/client.py
zipkin/config.py
zipkin/logging.py
zipkin/models.py
zipkin/resources/scribe.thrift
zipkin/resources/zipkinCore.thrift
zipkin/tests/__init__.py
zipkin/tests/bindings/__init__.py
zipkin/tests/bindings/test_flask.py
zipkin/tests/bindings/test_requests.py
zipkin/tests/bindings/test_xmlrpclib.py
zipkin/tests/test_client.py
zipkin/tests/test_logging.py
zipkin/tests/test_models.py
zipkin/tests/test_util.py
zipkin/tests/utils.py
zipkin/thread.py
zipkin/transport/__init__.py
zipkin/transport/httpclient.py
zipkin/transport/scribe.py
zipkin/transport/scribeclient.py
zipkin/util.py
zipkin/zipkin.py
zk-0.9.3.dist-info/LICENSE
zk-0.9.3.dist-info/METADATA
zk-0.9.3.dist-info/WHEEL
zk-0.9.3.dist-info/RECORD
