Metadata-Version: 2.1
Name: zk
Version: 0.9.3
Summary: zipkin
Home-page: https://github.com/Gandi/python-zipkin/
License: Apache
Keywords: zipkin,metrics,trace
Author: Gandi
Author-email: feedback@gandi.net
Requires-Python: >=3.7,<4.0
Classifier: License :: Other/Proprietary License
Classifier: Programming Language :: Python :: 3
Classifier: Programming Language :: Python :: 3.7
Classifier: Programming Language :: Python :: 3.8
Classifier: Programming Language :: Python :: 3.9
Classifier: Programming Language :: Python :: 3.10
Classifier: Programming Language :: Python :: 3.11
Classifier: Programming Language :: Python :: 3.12
Provides-Extra: celery
Provides-Extra: django
Provides-Extra: flask
Provides-Extra: psycopg2
Provides-Extra: pyramid
Provides-Extra: requests
Requires-Dist: celery (>=5.2.0,<6.0.0) ; (python_version < "3.11") and (extra == "celery")
Requires-Dist: celery (>=5.4.0,<6.0.0) ; (python_version >= "3.11") and (extra == "celery")
Requires-Dist: django (==3.2.25) ; (python_version < "3.11") and (extra == "django")
Requires-Dist: django (>=5.4.0,<6.0.0) ; (python_version >= "3.11") and (extra == "django")
Requires-Dist: flask (>=2.0.0,<3.0.0) ; (python_version < "3.11") and (extra == "flask")
Requires-Dist: flask (>=2.0.0,<3.0.0) ; (python_version >= "3.11") and (extra == "flask")
Requires-Dist: pyramid (>=1.7.0,<2.0.0) ; (python_version < "3.11") and (extra == "pyramid")
Requires-Dist: pyramid (>=2.0.2,<3.0.0) ; (python_version >= "3.11") and (extra == "pyramid")
Requires-Dist: requests (>=2.31.0,<3.0.0) ; (python_version < "3.11") and (extra == "requests")
Requires-Dist: requests (>=2.32.0,<3.0.0) ; (python_version >= "3.11") and (extra == "requests")
Requires-Dist: setuptools (>=64.0.0,<65.0.0) ; python_version < "3.11"
Requires-Dist: setuptools (>=74.0.0,<75.0.0) ; python_version >= "3.11"
Requires-Dist: six (>=1.16.0,<2.0.0)
Requires-Dist: thriftpy2 (>=0.5.2,<0.6.0)
